merlin_transcripts/__init__.py
merlin_transcripts/keccak.py
merlin_transcripts/merlin_transcript.py
merlin_transcripts/py.typed
merlin_transcripts/strobe.py
merlin_transcripts/test_merlin.py
merlin_transcripts-0.1.1.dist-info/METADATA
merlin_transcripts-0.1.1.dist-info/WHEEL
merlin_transcripts-0.1.1.dist-info/RECORD
