Metadata-Version: 2.1
Name: merlin-transcripts
Version: 0.1.1
Summary: merlin is a Python implementation of Merlin transcripts (https://merlin.cool)
License: MIT
Author: Nalin Bhardwaj
Author-email: nalinbhardwaj@nibnalin.me
Requires-Python: >=3.9,<4.0
Classifier: License :: OSI Approved :: MIT License
Classifier: Programming Language :: Python :: 3
Classifier: Programming Language :: Python :: 3.9
Classifier: Programming Language :: Python :: 3.10
Classifier: Programming Language :: Python :: 3.11
